{
  "pages": [
    {
      "pageName": "fgrfgdf",
      "pageDescription": "GDGDSGsDGDS",
      "id": 1
    }
  ],
  "CreatedPages": [
    {
      "pageContents": "<p>adidouovhdsiohvisdhivsnovsinvsionnvsvossvnsvnsovnsonvsoonvsovnsonvsnoovnsonvosnvsovosnvoosnvosnvosnvosnvosnvosovnosnvosonvosnvos</p>",
      "id": 1
    }
  ],
  "OnBoardingPages": [
    {
      "id": 1,
      "paigeLogo": "",
      "onBoardingBackPic": "",
      "onBoardingContents": "this is the froala blocks"
    },
    {
      "id": 2,
      "paigeLogo": "",
      "onBoardingBackPic": "",
      "onBoardingContents": "this is the froala blocks"
    },
    {
      "id": 3,
      "paigeLogo": "",
      "onBoardingBackPic": "",
      "onBoardingContents": "this is the froala blocks"
    },
    {
      "id": 4,
      "paigeLogo": "",
      "onBoardingBackPic": "",
      "onBoardingContents": "this is the froala blocks"
    }
  ]
}